MANIFEST.in
README.md
setup.py
ortografix/__init__.py
ortografix/main.py
ortografix.egg-info/PKG-INFO
ortografix.egg-info/SOURCES.txt
ortografix.egg-info/dependency_links.txt
ortografix.egg-info/entry_points.txt
ortografix.egg-info/not-zip-safe
ortografix.egg-info/requires.txt
ortografix.egg-info/top_level.txt
ortografix/exceptions/__init__.py
ortografix/exceptions/method.py
ortografix/exceptions/parameter.py
ortografix/logging/__init__.py
ortografix/logging/logging.yml
ortografix/model/__init__.py
ortografix/model/attention.py
ortografix/model/dataset.py
ortografix/model/decoder.py
ortografix/model/encoder.py
ortografix/model/transformer.py
ortografix/utils/__init__.py
ortografix/utils/config.py
ortografix/utils/constants.py
ortografix/utils/immutables.py
ortografix/utils/processing.py
ortografix/utils/time.py