Metadata-Version: 2.1
Name: ortografix
Version: 0.7.0
Summary: Seq2seq model with attention for automatic orthographic simplification
Home-page: https://github.com/akb89/ortografix
Author:  Alexandre Kabbach
Author-email: akb@3azouz.net
License: MIT
Download-URL: https://github.com/akb89/ortografix
Keywords: seq2seq,ortographic simplification
Platform: any
Classifier: Development Status :: 2 - Pre-Alpha
Classifier: Environment :: Web Environment
Classifier: Intended Audience :: Developers
Classifier: Intended Audience :: Education
Classifier: Intended Audience :: Science/Research
Classifier: License :: OSI Approved :: MIT License
Classifier: Natural Language :: English
Classifier: Operating System :: OS Independent
Classifier: Programming Language :: Python :: 3.5
Classifier: Programming Language :: Python :: 3.6
Classifier: Programming Language :: Python :: 3.7
Classifier: Programming Language :: Python :: 3.8
Classifier: Topic :: Scientific/Engineering :: Artificial Intelligence
Classifier: Topic :: Software Development :: Libraries :: Python Modules
